pytima/__init__.py
pytima/backtest.py
pytima/datasets.py
pytima-0.0.1.dist-info/LICENSE
pytima-0.0.1.dist-info/METADATA
pytima-0.0.1.dist-info/WHEEL
pytima-0.0.1.dist-info/top_level.txt
pytima-0.0.1.dist-info/RECORD
